frag_pele/__init__.py
frag_pele/constants.py
frag_pele/log_configure.ini
frag_pele/main.py
frag_pele/serie_handler.py
frag_pele/Analysis/__init__.py
frag_pele/Analysis/analyser.py
frag_pele/Analysis/backtrackConnectivity.py
frag_pele/Analysis/backtrackFragTrajectory.py
frag_pele/Analysis/compute_atom_atom_distance.py
frag_pele/Analysis/forcefield_analysis.py
frag_pele/Analysis/get_plots.py
frag_pele/Analysis/interaction_detector.py
frag_pele/Analysis/output_files.py
frag_pele/Analysis/rmsd_computer.py
frag_pele/Analysis/sidecahins_analyser.py
frag_pele/Banner/Detector.py
frag_pele/Banner/__init__.py
frag_pele/Covalent/__init__.py
frag_pele/Covalent/correct_pdb_to_covalent_res.py
frag_pele/Covalent/correct_rotamer_library.py
frag_pele/Covalent/correct_template_of_backbone_res.py
frag_pele/Covalent/pdb_corrector.py
frag_pele/Covalent/prepare_pdb_to_cov_heteroatom.py
frag_pele/Growing/__init__.py
frag_pele/Growing/add_fragment_from_pdbs.py
frag_pele/Growing/bestStructs.py
frag_pele/Growing/simulations_linker.py
frag_pele/Growing/template_fragmenter.py
frag_pele/Growing/template_selector.py
frag_pele/Growing/AddingFragHelpers/__init__.py
frag_pele/Growing/AddingFragHelpers/atom_constants.py
frag_pele/Growing/AddingFragHelpers/complex_to_prody.py
frag_pele/Growing/AddingFragHelpers/pdb_joiner.py
frag_pele/Helpers/__init__.py
frag_pele/Helpers/center_of_mass.py
frag_pele/Helpers/check_constants.py
frag_pele/Helpers/checker.py
frag_pele/Helpers/clusterizer.py
frag_pele/Helpers/conda_deploy.py
frag_pele/Helpers/constraints.py
frag_pele/Helpers/correct_fragment_names.py
frag_pele/Helpers/create_templates.py
frag_pele/Helpers/find_dihedrals.py
frag_pele/Helpers/folder_handler.py
frag_pele/Helpers/helpers.py
frag_pele/Helpers/plop_rot_temp.py
frag_pele/Helpers/runner.py
frag_pele/Helpers/templatize.py
frag_pele/PlopRotTemp_S_2017/PlopRotTemp.py
frag_pele/PlopRotTemp_S_2017/__init__.py
frag_pele/PlopRotTemp_S_2017/ligand_prep.py
frag_pele/PlopRotTemp_S_2017/main.py
frag_pele-3.1.4.dist-info/LICENSE
frag_pele-3.1.4.dist-info/METADATA
frag_pele-3.1.4.dist-info/WHEEL
frag_pele-3.1.4.dist-info/top_level.txt
frag_pele-3.1.4.dist-info/RECORD
