Metadata-Version: 2.1
Name: frag-pele
Version: 3.1.4
Summary: FragPELE, a new tool for in silico hit-to-lead drug design, capable of growing a frag_pelement into a core while exploring the protein-ligand conformational space
Home-page: https://github.com/carlesperez94/frag_pele/
Author: Carles Perez Lopez, Daniel Soler Viladrich
Author-email: daniel.soler@nostrumbiodiscovery.com, carlesperez94@gmail.com
License: UNKNOWN
Project-URL: Documentation, https://carlesperez94.github.io/frag_pele/
Project-URL: Source, https://carlesperez94.github.io/frag_pele/
Project-URL: Tracker, https://github.com/carlesperez94/frag_pele/issues
Platform: UNKNOWN
Classifier: Programming Language :: Python :: 3
Classifier: Programming Language :: Python :: 2.7
Classifier: License :: OSI Approved :: MIT License
Classifier: Operating System :: POSIX :: Linux
Classifier: Intended Audience :: Science/Research
License-File: LICENSE
Requires-Dist: cython
Requires-Dist: numpy
Requires-Dist: scipy
Requires-Dist: matplotlib
Requires-Dist: biopython
Requires-Dist: pandas
Requires-Dist: prody (==1.10)
Requires-Dist: pytest
Requires-Dist: AdaptivePELE (>=1.7.1)
Requires-Dist: lib-prep (>=1.1.2)
Requires-Dist: mdtraj
Requires-Dist: peleffy (>=1.4.3)
